{"recenttracks":{"track":[{"artist":{"#text":"The Weeknd","mbid":"c8b03190-306c-4120-bb0b-6f2ebfc06ea9"},"name":"Outside","streamable":"0","mbid":"","album":{"#text":"Echoes Of Silence","mbid":"2e9e61c6-cb68-48f1-a721-7e12264b1511"},"url":"http:\/\/www.last.fm\/music\/The+Weeknd\/_\/Outside","image":[{"#text":"http:\/\/userserve-ak.last.fm\/serve\/34s\/72341614.png","size":"small"},{"#text":"http:\/\/userserve-ak.last.fm\/serve\/64s\/72341614.png","size":"medium"},{"#text":"http:\/\/userserve-ak.last.fm\/serve\/126\/72341614.png","size":"large"},{"#text":"http:\/\/userserve-ak.last.fm\/serve\/300x300\/72341614.png","size":"extralarge"}],"date":{"#text":"3 Feb 2012, 14:02","uts":"1328277750"}},{"artist":{"#text":"The Weeknd","mbid":"c8b03190-306c-4120-bb0b-6f2ebfc06ea9"},"name":"Montreal","streamable":"0","mbid":"","album":{"#text":"Echoes Of Silence","mbid":"2e9e61c6-cb68-48f1-a721-7e12264b1511"},"url":"http:\/\/www.last.fm\/music\/The+Weeknd\/_\/Montreal","image":[{"#text":"http:\/\/userserve-ak.last.fm\/serve\/34s\/72341614.png","size":"small"},{"#text":"http:\/\/userserve-ak.last.fm\/serve\/64s\/72341614.png","size":"medium"},{"#text":"http:\/\/userserve-ak.last.fm\/serve\/126\/72341614.png","size":"large"},{"#text":"http:\/\/userserve-ak.last.fm\/serve\/300x300\/72341614.png","size":"extralarge"}],"date":{"#text":"3 Feb 2012, 13:26","uts":"1328275569"}},{"artist":{"#text":"Christmas Hits","mbid":""},"name":"Last Christmas","streamable":"1","mbid":"","album":{"#text":"40 Worlds Greatest Christmas Hits 2011  - The only Xmas Hits album you'll ever need","mbid":""},"url":"http:\/\/www.last.fm\/music\/Christmas+Hits\/_\/Last+Christmas","image":[{"#text":"http:\/\/userserve-ak.last.fm\/serve\/34s\/69976530.jpg","size":"small"},{"#text":"http:\/\/userserve-ak.last.fm\/serve\/64s\/69976530.jpg","size":"medium"},{"#text":"http:\/\/userserve-ak.last.fm\/serve\/126\/69976530.jpg","size":"large"},{"#text":"http:\/\/userserve-ak.last.fm\/serve\/300x300\/69976530.jpg","size":"extralarge"}],"date":{"#text":"3 Feb 2012, 13:03","uts":"1328274185"}},{"artist":{"#text":"The Doors","mbid":"9efff43b-3b29-4082-824e-bc82f646f93d"},"name":"The Unknown Soldier","streamable":"1","mbid":"","album":{"#text":"Waiting for the Sun","mbid":"355ceb72-1ed8-466e-8fbe-3f93138aa189"},"url":"http:\/\/www.last.fm\/music\/The+Doors\/_\/The+Unknown+Soldier","image":[{"#text":"http:\/\/userserve-ak.last.fm\/serve\/34s\/39043747.png","size":"small"},{"#text":"http:\/\/userserve-ak.last.fm\/serve\/64s\/39043747.png","size":"medium"},{"#text":"http:\/\/userserve-ak.last.fm\/serve\/126\/39043747.png","size":"large"},{"#text":"http:\/\/userserve-ak.last.fm\/serve\/300x300\/39043747.png","size":"extralarge"}],"date":{"#text":"3 Feb 2012, 12:59","uts":"1328273978"}},{"artist":{"#text":"Jamie Cullum","mbid":"b10806de-2198-4313-af6a-13df4acb912f"},"name":"If I Ruled The World","streamable":"1","mbid":"","album":{"#text":"The Pursuit","mbid":"31d7b03f-e482-48f8-a1f4-41b11b0f0d74"},"url":"http:\/\/www.last.fm\/music\/Jamie+Cullum\/_\/If+I+Ruled+The+World","image":[{"#text":"http:\/\/userserve-ak.last.fm\/serve\/34s\/69337102.png","size":"small"},{"#text":"http:\/\/userserve-ak.last.fm\/serve\/64s\/69337102.png","size":"medium"},{"#text":"http:\/\/userserve-ak.last.fm\/serve\/126\/69337102.png","size":"large"},{"#text":"http:\/\/userserve-ak.last.fm\/serve\/300x300\/69337102.png","size":"extralarge"}],"date":{"#text":"3 Feb 2012, 12:55","uts":"1328273701"}},{"artist":{"#text":"Deep Purple","mbid":"79491354-3d83-40e3-9d8e-7592d58d790a"},"name":"Burn (Live In Austria)","streamable":"1","mbid":"","album":{"#text":"Made In Europe","mbid":"850f0036-bd18-465c-ac9c-898852e2c46f"},"url":"http:\/\/www.last.fm\/music\/Deep+Purple\/_\/Burn+%28Live+In+Austria%29","image":[{"#text":"http:\/\/userserve-ak.last.fm\/serve\/34s\/72860216.jpg","size":"small"},{"#text":"http:\/\/userserve-ak.last.fm\/serve\/64s\/72860216.jpg","size":"medium"},{"#text":"http:\/\/userserve-ak.last.fm\/serve\/126\/72860216.jpg","size":"large"},{"#text":"http:\/\/userserve-ak.last.fm\/serve\/300x300\/72860216.jpg","size":"extralarge"}],"date":{"#text":"3 Feb 2012, 12:47","uts":"1328273248"}},{"artist":{"#text":"Train","mbid":"bfd5aec5-62a2-4560-a316-7c46c17babda"},"name":"Get Out","streamable":"1","mbid":"","album":{"#text":"For Me, It's You","mbid":"7fecbc33-9881-4312-be0b-c20273e711df"},"url":"http:\/\/www.last.fm\/music\/Train\/_\/Get+Out","image":[{"#text":"http:\/\/userserve-ak.last.fm\/serve\/34s\/72628416.png","size":"small"},{"#text":"http:\/\/userserve-ak.last.fm\/serve\/64s\/72628416.png","size":"medium"},{"#text":"http:\/\/userserve-ak.last.fm\/serve\/126\/72628416.png","size":"large"},{"#text":"http:\/\/userserve-ak.last.fm\/serve\/300x300\/72628416.png","size":"extralarge"}],"date":{"#text":"3 Feb 2012, 12:44","uts":"1328273043"}},{"artist":{"#text":"The Doors","mbid":"9efff43b-3b29-4082-824e-bc82f646f93d"},"name":"People Are Strange","streamable":"1","mbid":"","album":{"#text":"Greatest Hits","mbid":"5c740868-c481-301d-8871-b3da741fe9ad"},"url":"http:\/\/www.last.fm\/music\/The+Doors\/_\/People+Are+Strange","image":[{"#text":"http:\/\/userserve-ak.last.fm\/serve\/34s\/39619023.png","size":"small"},{"#text":"http:\/\/userserve-ak.last.fm\/serve\/64s\/39619023.png","size":"medium"},{"#text":"http:\/\/userserve-ak.last.fm\/serve\/126\/39619023.png","size":"large"},{"#text":"http:\/\/userserve-ak.last.fm\/serve\/300x300\/39619023.png","size":"extralarge"}],"date":{"#text":"3 Feb 2012, 12:41","uts":"1328272909"}},{"artist":{"#text":"Stereophonics","mbid":"0bfba3d3-6a04-4779-bb0a-df07df5b0558"},"name":"Have A Nice Day","streamable":"1","mbid":"","album":{"#text":"Just Enough Education to Perform","mbid":"b8c5f088-3fc7-39ed-ab9d-dc96e3e457d6"},"url":"http:\/\/www.last.fm\/music\/Stereophonics\/_\/Have+A+Nice+Day","image":[{"#text":"http:\/\/userserve-ak.last.fm\/serve\/34s\/70116196.png","size":"small"},{"#text":"http:\/\/userserve-ak.last.fm\/serve\/64s\/70116196.png","size":"medium"},{"#text":"http:\/\/userserve-ak.last.fm\/serve\/126\/70116196.png","size":"large"},{"#text":"http:\/\/userserve-ak.last.fm\/serve\/300x300\/70116196.png","size":"extralarge"}],"date":{"#text":"3 Feb 2012, 12:15","uts":"1328271318"}},{"artist":{"#text":"Lazlo Bane","mbid":"63f38f77-9aae-4e1b-8947-aca325b7759f"},"name":"Superman","streamable":"1","mbid":"","album":{"#text":"All The Time In The World","mbid":"ff5f3a25-22d7-441a-8105-f9d4a05c7362"},"url":"http:\/\/www.last.fm\/music\/Lazlo+Bane\/_\/Superman","image":[{"#text":"http:\/\/userserve-ak.last.fm\/serve\/34s\/45079785.jpg","size":"small"},{"#text":"http:\/\/userserve-ak.last.fm\/serve\/64s\/45079785.jpg","size":"medium"},{"#text":"http:\/\/userserve-ak.last.fm\/serve\/126\/45079785.jpg","size":"large"},{"#text":"http:\/\/userserve-ak.last.fm\/serve\/300x300\/45079785.jpg","size":"extralarge"}],"date":{"#text":"3 Feb 2012, 12:11","uts":"1328271088"}}],"@attr":{"user":"Grogs","page":"1","perPage":"10","totalPages":"10274","total":"102738"}}}
